README.md
setup.cfg
setup.py
NCP_Geolocation/NCP_Geolocation_API.py
NCP_Geolocation/__init__.py
NCP_Geolocation.egg-info/PKG-INFO
NCP_Geolocation.egg-info/SOURCES.txt
NCP_Geolocation.egg-info/dependency_links.txt
NCP_Geolocation.egg-info/requires.txt
NCP_Geolocation.egg-info/top_level.txt