Metadata-Version: 1.1
Name: NCP-Geolocation
Version: 0.11
Summary: This is for Geolocation service of Naver Cloud Platfrom
Home-page: https://github.com/ultimatelife/NCP_Geolocation.git
Author: geonwoo.kim
Author-email: drama0708@gmail.com
License: Naver Cloud Platform
Platform: UNKNOWN
Classifier: Programming Language :: Python :: 3
